{
	"0": {
		"color": "#FF0000",
		"name": "lianpu-hualian-ting"
	},
	"1": {
		"color": "#00FF00",
		"name": "ganpi-jingzhi-ting"
	},
	"2": {
		"color": "#0000FF",
		"name": "ganpi-old-ping"
	},
	"3": {
		"color": "#FFFF00",
		"name": "superx-old-ting"
	},
	"4": {
		"color": "#00FFFF",
		"name": "chunsheng-ting"
	},
	"5": {
		"color": "#FF00FF",
		"name": "chunsheng-ping"
	},
	"6": {
		"color": "#FFC125",
		"name": "danshuang-ting"
	},
	"7": {
		"color": "#F0FFF0",
		"name": "danshuang-ping"
	},
	"8": {
		"color": "#FFB6C1",
		"name": "laoxue-ting"
	},
	"9": {
		"color": "#EE00EE",
		"name": "jiangxin-ping"
	},
	"10": {
		"color": "#DAA520",
		"name": "maersilv-ping"
	},
	"11": {
		"color": "#D2691E",
		"name": "shengpi-ting"
	},
	"12": {
		"color": "#CAFF70",
		"name": "chunpi-ting"
	},
	"13": {
		"color": "#BF3EFF",
		"name": "jinwei-ting"
	},
	"14": {
		"color": "#9F79EE",
		"name": "superx-ting"
	}
}
